{
  "intro": [
    "我毕业于香港浸会大学当代中国研究专业，本科为广东外语外贸大学社会工作。跨学科的学习经历让我既能用数据与逻辑拆解用户需求，也能用人文视角理解内容背后的情感连接。",
    "过去一年，我深耕海外房产与留学赛道，负责小红书、抖音、视频号、微博、豆瓣等多平台账号的搭建与运营。从 0 到 1 打造粤语英国卖房账号，单平台粉丝增长 9000+；主导留学账号矩阵，月促成签单十余单，累计成交金额超 60 万。",
    "我熟悉内容全链路：选题策划、脚本撰写、图文排版、达人合作、广告投放、数据复盘，也具备粤语与英语内容输出能力，能够胜任内容运营、新媒体策划、PR 传播等岗位。"
  ],
  "education": [
    {
      "school": "香港浸会大学",
      "degree": "当代中国研究 硕士",
      "location": "香港，中国",
      "date": "2023.09 - 2024.10"
    },
    {
      "school": "广东外语外贸大学",
      "degree": "社会工作 学士",
      "location": "广州，中国",
      "date": "2019.09 - 2023.07"
    }
  ]
}